LICENSE
MANIFEST.in
README.rst
setup.cfg
setup.py
sprockets/__init__.py
sprockets.clients.postgresql.egg-info/PKG-INFO
sprockets.clients.postgresql.egg-info/SOURCES.txt
sprockets.clients.postgresql.egg-info/dependency_links.txt
sprockets.clients.postgresql.egg-info/namespace_packages.txt
sprockets.clients.postgresql.egg-info/not-zip-safe
sprockets.clients.postgresql.egg-info/requires.txt
sprockets.clients.postgresql.egg-info/top_level.txt
sprockets/clients/__init__.py
sprockets/clients/postgresql/__init__.py