Metadata-Version: 1.1
Name: sprockets.clients.postgresql
Version: 1.0.1
Summary: PostgreSQL client library wrapper providing environment variable based configuration
Home-page: https://github.com/sprockets/sprockets.clients.postgresql.git
Author: AWeber Communications
Author-email: api@aweber.com
License: Copyright (c) 2014 AWeber Communications
